stups_tokens-1.0.19.dist-info/DESCRIPTION.rst
stups_tokens-1.0.19.dist-info/METADATA
stups_tokens-1.0.19.dist-info/RECORD
stups_tokens-1.0.19.dist-info/WHEEL
stups_tokens-1.0.19.dist-info/metadata.json
stups_tokens-1.0.19.dist-info/top_level.txt
tokens/__init__.py
