Metadata-Version: 2.0
Name: stups-tokens
Version: 1.0.19
Summary: Python library to manage OAuth access tokens
Home-page: https://github.com/zalando-stups/python-tokens
Author: Henning Jacobs
Author-email: henning.jacobs@zalando.de
License: Apache License Version 2.0
Platform: UNKNOWN
Classifier: Programming Language :: Python
Classifier: Programming Language :: Python :: 2.7
Classifier: Programming Language :: Python :: 3.4
Classifier: Programming Language :: Python :: 3.5
Classifier: Development Status :: 4 - Beta
Classifier: Intended Audience :: Developers
Classifier: Operating System :: OS Independent
Requires-Dist: requests
Provides-Extra: tests
Requires-Dist: flake8; extra == 'tests'
